blobfile/VERSION
blobfile/__init__.py
blobfile/_azure.py
blobfile/_common.py
blobfile/_context.py
blobfile/_gcp.py
blobfile/_ops.py
blobfile/_ops_test.py
blobfile/_xml.py
blobfile/_xml_test.py
blobfile/py.typed
blobfile-3.0.0.dist-info/LICENSE
blobfile-3.0.0.dist-info/METADATA
blobfile-3.0.0.dist-info/WHEEL
blobfile-3.0.0.dist-info/top_level.txt
blobfile-3.0.0.dist-info/RECORD
