Metadata-Version: 2.1
Name: blobfile
Version: 3.0.0
Summary: Read GCS, ABS and local paths with the same interface, clone of tensorflow.io.gfile
Home-page: https://github.com/christopher-hesse/blobfile
Author: Christopher Hesse
License: Public Domain
Requires-Python: >=3.8.0
License-File: LICENSE
Requires-Dist: pycryptodomex>=3.8
Requires-Dist: urllib3<3,>=1.25.3
Requires-Dist: lxml>=4.9
Requires-Dist: filelock>=3.0
